kia_uvo_api/__init__.py
kia_uvo_api/auth_error.py
kia_uvo_api/ca.py
kia_uvo_api/ca_hyundai.py
kia_uvo_api/ca_kia.py
kia_uvo_api/const.py
kia_uvo_api/us_kia.py
kia_uvo_api-1.1.8.dist-info/METADATA
kia_uvo_api-1.1.8.dist-info/WHEEL
kia_uvo_api-1.1.8.dist-info/top_level.txt
kia_uvo_api-1.1.8.dist-info/RECORD
