Metadata-Version: 2.1
Name: kia-uvo-api
Version: 1.1.8
Summary: Kia Uvo/Hyundai Blue Link Api Wrapper
Home-page: https://github.com/dahlb/kia_uvo
Author: Brendan Dahl
Author-email: dahl.brendan@gmail.com
License: UNKNOWN
Project-URL: Bug Reports, https://github.com/dahlb/kia_uvo/issues
Project-URL: Source, https://github.com/dahlb/kia_uvo
Keywords: Kia,Uvo,Api,Hyundai
Platform: UNKNOWN
Classifier: Development Status :: 4 - Beta
Classifier: Framework :: AsyncIO
Classifier: License :: OSI Approved :: MIT License
Classifier: Natural Language :: English
Classifier: Intended Audience :: Developers
Classifier: Programming Language :: Python :: 3
Classifier: Operating System :: MacOS :: MacOS X
Classifier: Operating System :: Microsoft :: Windows
Requires-Python: >=3.9, <4
Requires-Dist: aiohttp (>=3.8.1)
